impyrium/__init__.py
impyrium/__main__.py
impyrium/common_css.py
impyrium/control.py
impyrium/device_thread.py
impyrium/helpers.py
impyrium/inputless_combo.py
impyrium/keybinding_widget.py
impyrium/keycombo_dialog.py
impyrium/main_menu.py
impyrium/pyqt6_key_map.py
impyrium/router.py
impyrium/signals.py
impyrium/text_display.py
impyrium/thread_safe_queue.py
impyrium/work_queue.py
impyrium/worker_thread.py
impyrium/default_files/__init__.py
impyrium/default_files/ahk_get_file_script.py
impyrium/default_files/default_file.py
impyrium/default_files/defaults.py
impyrium/default_files/json_file_defaults.py
impyrium/default_files/py_file_defaults.py
impyrium/images/__init__.py
impyrium/popups/__init__.py
impyrium/popups/build_a_popup.py
impyrium/popups/device_info_popup.py
impyrium/popups/popup.py
impyrium/popups/single_select_popup.py
impyrium/popups/text_popup.py
impyrium/widgets/__init__.py
impyrium/widgets/control_menu.py
impyrium/widgets/custom_button.py
impyrium/widgets/device_selector.py
impyrium/widgets/item_scroll_view.py
impyrium/widgets/main_impyrium.py
impyrium-1.2.2.dist-info/licenses/LICENSE
impyrium-1.2.2.dist-info/METADATA
impyrium-1.2.2.dist-info/WHEEL
impyrium-1.2.2.dist-info/top_level.txt
impyrium-1.2.2.dist-info/RECORD
