Metadata-Version: 2.4
Name: impyrium
Version: 1.2.2
Summary: A tool to setup device controls
Home-page: https://github.com/c3n3/impyrium
Author: Caden Churchman
Author-email: ccaden21@gmail.com
Project-URL: Bug Tracker, https://github.com/c3n3/impyrium/issues
Classifier: Programming Language :: Python :: 3
Classifier: License :: OSI Approved :: MIT License
Classifier: Operating System :: POSIX :: Linux
Requires-Python: >=3.6
License-File: LICENSE
Requires-Dist: PySide6==6.9.1
Requires-Dist: py_global_shortcuts==0.1.2
Dynamic: license-file
